shift/shift_register.v
module shift_register(
    input clk,       
    input reset,  
    input load,   
    input [3:0] d,
    input si,   
    output reg [3:0] q 
    //formatting the modules inputs and outputs
);

	always @(posedge clk or posedge reset) begin
	        if (reset) begin
			q <= 4'b0000;  // Reset shift register on reset signal
		end else if (load) begin
			q<=d; //updates with the value of d?
		end else begin
			q<={si,q[3:1]}; //shift bits to right
		end
	end
endmodule

shift/tb_shit_register.v
module tb_shift_register;

	/* Create a regular pulsing clock. */
	reg clk = 0;
	always #5 clk = ~clk; // Toggle clock every 5 time units

	// Test inputs
	reg reset = 0;
	reg load = 0;
	reg si = 0;
	reg [3:0] d = 0;

	// Output wire
	wire [3:0] q;

	// Instantiate the shift register
	shift_register uut (
		.clk(clk),
		.reset(reset),
		.load(load),
		.d(d),
		.si(si),
		.q(q)
	);

	// Initial block for stimulus
	initial begin
		// Monitor changes
		$monitor("At time %t: reset = %b, load = %b, si = %b, d = %b, q = %b",
			$time, reset, load, si, d, q);

	// Reset the shift register
	reset = 1; #10;
	reset = 0; #10;

	// Load data into the shift register
	load = 1; d = 4'b1001; #10;
	load = 0; si = 1; #10;

	// Shift operation
	#10;
	si = 0; #10;
	si = 1; #10;

	// Final reset
	reset = 1; #10;
	reset = 0; #10;

	// Finish simulation
	$finish;
end

	// VCD dump for waveform generation
	initial begin
		$dumpfile("shift_register.vcd");
		$dumpvars(0, tb_shift_register);
	end
endmodule

shift/shift_register.vcd
$date
	Fri Jul 12 15:10:40 2024
$end
$version
	Icarus Verilog
$end
$timescale
	1s
$end
$scope module tb_shift_register $end
$var wire 4 ! q [3:0] $end
$var reg 1 " clk $end
$var reg 4 # d [3:0] $end
$var reg 1 $ load $end
$var reg 1 % reset $end
$var reg 1 & si $end
$scope module uut $end
$var wire 1 " clk $end
$var wire 4 ' d [3:0] $end
$var wire 1 $ load $end
$var wire 1 % reset $end
$var wire 1 & si $end
$var reg 4 ( q [3:0] $end
$upscope $end
$upscope $end
$enddefinitions $end
#0
$dumpvars
b0 (
b0 '
0&
1%
0$
b0 #
0"
b0 !
$end
#5
1"
#10
0"
0%
#15
1"
#20
0"
b1001 #
b1001 '
1$
#25
b1001 !
b1001 (
1"
#30
0"
1&
0$
#35
b1100 !
b1100 (
1"
#40
0"
#45
b1110 !
b1110 (
1"
#50
0"
0&
#55
b111 !
b111 (
1"
#60
0"
1&
#65
b1011 !
b1011 (
1"
#70
b0 !
b0 (
0"
1%
#75
1"
#80
0"
0%
#85
b1000 !
b1000 (
1"
